repo_parser/__init__.py
repo_parser/cli.py
repo_parser/filesystem.py
repo_parser/processor.py
repo_parser/resource.py
repo_parser/templates/idr.md
repo_parser-0.0.3.dist-info/entry_points.txt
repo_parser-0.0.3.dist-info/licenses/LICENSE
repo_parser-0.0.3.dist-info/WHEEL
repo_parser-0.0.3.dist-info/METADATA
repo_parser-0.0.3.dist-info/RECORD
