Metadata-Version: 2.4
Name: repo-parser
Version: 0.0.3
Summary: A library for extracting metadata out of a source repository.
Author-email: William Lachance <wlach@protonmail.com>
Requires-Python: >=3.11
Classifier: License :: OSI Approved :: MIT License
License-File: LICENSE
Requires-Dist: GitPython
Requires-Dist: jinja2
Requires-Dist: python-slugify
Requires-Dist: typer
Project-URL: Home, https://github.com/wlach/repo-parser
